CTkQrCode/__init__.py
CTkQrCode/ctkqrcode.py
ctkqrcode-0.1.0.dist-info/METADATA
ctkqrcode-0.1.0.dist-info/WHEEL
ctkqrcode-0.1.0.dist-info/top_level.txt
ctkqrcode-0.1.0.dist-info/RECORD
