Metadata-Version: 2.4
Name: CTkQrCode
Version: 0.1.0
Summary: A CustomTkinter widget for generating customizable QR Codes easily.
Author-email: Matin <matinyarzadeh13@gmail.com>
License-Expression: MIT
Project-URL: Homepage, https://github.com/hu-matin/CTkQrCode
Project-URL: Bug Tracker, https://github.com/hu-matin/CTkQrCode/issues
Keywords: customtkinter,qrcode,widget,gui
Classifier: Programming Language :: Python :: 3
Classifier: Operating System :: OS Independent
Classifier: Topic :: Software Development
Requires-Python: >=3.6
Requires-Dist: qrcode
Requires-Dist: customtkinter
Requires-Dist: Pillow
